dorieh/__init__.py
dorieh/version.py
dorieh/census/__init__.py
dorieh/census/assemble_data.py
dorieh/census/calculate_density.py
dorieh/census/census_info.py
dorieh/census/cli.py
dorieh/census/do_qc.py
dorieh/census/exceptions.py
dorieh/census/interpolate_data.py
dorieh/census/query.py
dorieh/census/tigerweb.py
dorieh/census/utils.py
dorieh/census/write_data.py
dorieh/census/data/__init__.py
dorieh/census/data/load_data.py
dorieh/cms/__init__.py
dorieh/cms/aggregates.py
dorieh/cms/create_schema_config.py
dorieh/cms/duplicates.py
dorieh/cms/fts2yaml.py
dorieh/cms/init_cms_db.py
dorieh/cms/mcr_data_loader.py
dorieh/cms/random_selector.py
dorieh/cms/registry.py
dorieh/cms/table_population.py
dorieh/cms/models/mbsf_ab_2015.yaml
dorieh/cms/models/medicaid.yaml
dorieh/cms/models/medicare.yaml
dorieh/cms/models/medicare_cms.yaml
dorieh/cms/models/medicare_legacy.yaml
dorieh/cms/tools/__init__.py
dorieh/cms/tools/mcr_combine_tables.py
dorieh/cms/tools/mcr_create_test_data.py
dorieh/cms/tools/mcr_file.py
dorieh/cms/tools/mcr_fts2csv.py
dorieh/cms/tools/mcr_fts2db.py
dorieh/cms/tools/mcr_registry.py
dorieh/cms/tools/mcr_sas.py
dorieh/cms/tools/mcr_sas2db.py
dorieh/cms/tools/mcr_sas2yaml.py
dorieh/cms/tools/medpar_converter.py
dorieh/cwl/add_daily_data.cwl
dorieh/cwl/add_data.cwl
dorieh/cwl/aggregate_daily.cwl
dorieh/cwl/aggregate_one_file.cwl
dorieh/cwl/aggregate_wustl.cwl
dorieh/cwl/airnow.cwl
dorieh/cwl/airnow_local_shapes.cwl
dorieh/cwl/alter_database.cwl
dorieh/cwl/aqs.cwl
dorieh/cwl/build_gridmet_model.cwl
dorieh/cwl/census_assemble.cwl
dorieh/cwl/census_density.cwl
dorieh/cwl/census_ingest.cwl
dorieh/cwl/census_interpolate.cwl
dorieh/cwl/census_qc.cwl
dorieh/cwl/census_workflow.cwl
dorieh/cwl/census_write.cwl
dorieh/cwl/change_owner.cwl
dorieh/cwl/create.cwl
dorieh/cwl/download.cwl
dorieh/cwl/download_airnow.cwl
dorieh/cwl/download_aqs.cwl
dorieh/cwl/ensure_resource.cwl
dorieh/cwl/expand_aqs.cwl
dorieh/cwl/export.cwl
dorieh/cwl/get_shapes.cwl
dorieh/cwl/grant.cwl
dorieh-0.4.3.dist-info/licenses/LICENSE
dorieh-0.4.3.dist-info/METADATA
dorieh-0.4.3.dist-info/WHEEL
dorieh-0.4.3.dist-info/entry_points.txt
dorieh-0.4.3.dist-info/top_level.txt
dorieh-0.4.3.dist-info/RECORD
