Metadata-Version: 2.4
Name: dorieh
Version: 0.4.3
Summary: Dorieh Data Engineering Platform
Home-page: https://github.com/ForomePlatform/dorieh
Author: Michael A Bouzinier
Author-email: mbouzinier@g.harvard.edu
License: Apache 2.0
Classifier: Programming Language :: Python :: 3
Classifier: License :: OSI Approved :: Apache Software License
Classifier: Operating System :: OS Independent
Requires-Python: >=3.12
License-File: LICENSE
Requires-Dist: aiohttp
Requires-Dist: argcomplete>=1.12.1
Requires-Dist: boto3
Requires-Dist: certifi>=2024.7.4
Requires-Dist: cwltest>=2.0.20200626112502
Requires-Dist: cwltool>=3.0.20200710214758
Requires-Dist: deprecated
Requires-Dist: fiona>=1.10.1
Requires-Dist: fsspec
Requires-Dist: geopandas
Requires-Dist: geopy
Requires-Dist: GitPython
Requires-Dist: googlesearch-python
Requires-Dist: graphviz>=0.14.2
Requires-Dist: h5py
Requires-Dist: hydra-core
Requires-Dist: humanfriendly>=8.2
Requires-Dist: importlib-metadata>=2.0.0
Requires-Dist: isodate>=0.6.0
Requires-Dist: Markdown>=2.6.11
Requires-Dist: marko
Requires-Dist: MarkupSafe>=1.1.1
Requires-Dist: mypy-extensions>=0.4.3
Requires-Dist: myst-parser
Requires-Dist: netCDF4
Requires-Dist: numpy
Requires-Dist: openpyxl
Requires-Dist: pandas
Requires-Dist: paramiko
Requires-Dist: pyarrow
Requires-Dist: psutil>=5.7.2
Requires-Dist: psycopg2-binary>=2.8.6
Requires-Dist: PyGithub
Requires-Dist: pyresourcepool
Requires-Dist: pyshp
Requires-Dist: pytest
Requires-Dist: python-dateutil>=2.8.1
Requires-Dist: PyYAML>=5.3.1
Requires-Dist: rasterstats
Requires-Dist: requests>=2.32.4
Requires-Dist: rioxarray
Requires-Dist: rtree
Requires-Dist: ruamel.yaml>=0.16.5
Requires-Dist: ruamel.yaml.clib>=0.2.2
Requires-Dist: sas7bdat
Requires-Dist: schema-salad>=7.0.20200811075006
Requires-Dist: setproctitle>=1.1.10
Requires-Dist: shapely>=2.1.2
Requires-Dist: shellescape>=3.4.1
Requires-Dist: six>=1.15.0
Requires-Dist: sortedcontainers
Requires-Dist: sphinx
Requires-Dist: sphinx_paramlinks
Requires-Dist: sphinx_rtd_theme
Requires-Dist: sphinxcontrib-mermaid
Requires-Dist: sqlparse
Requires-Dist: tqdm>=4.66.3
Requires-Dist: typing-extensions
Requires-Dist: tzlocal>=1.5.1
Requires-Dist: unicodecsv>=0.14.1
Requires-Dist: urllib3>=2.5.0
Requires-Dist: websocket-client>=0.57.0
Requires-Dist: sshtunnel
Requires-Dist: xarray
Requires-Dist: xlrd
Provides-Extra: fst
Requires-Dist: rpy2; extra == "fst"
Provides-Extra: spark
Requires-Dist: pyspark; extra == "spark"
Requires-Dist: pyhive; extra == "spark"
Dynamic: author
Dynamic: author-email
Dynamic: classifier
Dynamic: description
Dynamic: description-content-type
Dynamic: home-page
Dynamic: license
Dynamic: license-file
Dynamic: provides-extra
Dynamic: requires-dist
Dynamic: requires-python
Dynamic: summary
